Metadata-Version: 2.1
Name: django-anysearch-dsl
Version: 7.2.2.1
Summary: Wrapper around elasticsearch-dsl and opensearch-dsl for Django models
Home-page: https://github.com/django-anysearch/django-anysearch-dsl
Author: Sabricot
Maintainer: Artur Barseghyan
License: Apache Software License 2.0
Keywords: django elasticsearch elasticsearch-dsl
Classifier: Development Status :: 3 - Alpha
Classifier: Framework :: Django
Classifier: Framework :: Django :: 2.2
Classifier: Framework :: Django :: 3.0
Classifier: Framework :: Django :: 3.1
Classifier: Framework :: Django :: 3.2
Classifier: Framework :: Django :: 4.0
Classifier: Framework :: Django :: 4.1
Classifier: Intended Audience :: Developers
Classifier: License :: OSI Approved :: Apache Software License
Classifier: Natural Language :: English
Classifier: Programming Language :: Python :: 3
Classifier: Programming Language :: Python :: 3.6
Classifier: Programming Language :: Python :: 3.7
Classifier: Programming Language :: Python :: 3.8
Classifier: Programming Language :: Python :: 3.9
Classifier: Programming Language :: Python :: 3.10
Classifier: Programming Language :: Python :: 3.11
License-File: LICENSE
License-File: AUTHORS.rst
Requires-Dist: six
Requires-Dist: anysearch (>=0.2.2)
Provides-Extra: elasticsearch
Requires-Dist: elasticsearch ; extra == 'elasticsearch'
Requires-Dist: elasticsearch-dsl ; extra == 'elasticsearch'
Provides-Extra: opensearch
Requires-Dist: opensearch-py ; extra == 'opensearch'
Requires-Dist: opensearch-dsl ; extra == 'opensearch'
